MANIFEST.in
README.md
setup.py
project_americana_api_rest.egg-info/PKG-INFO
project_americana_api_rest.egg-info/SOURCES.txt
project_americana_api_rest.egg-info/dependency_links.txt
project_americana_api_rest.egg-info/requires.txt
project_americana_api_rest.egg-info/top_level.txt
src/__main__.py
src/app.py
src/config/__init__.py
src/controllers/datafields_controllers.py
src/controllers/logIn_controllers.py
src/controllers/mail_controller.py
src/controllers/mobile_controllers.py
src/controllers/recibos_controllers.py
src/models/datafields_models.py
src/models/mobile_models.py
src/models/recibos_models.py
src/routes/datafields_routes.py
src/routes/logIn_routes.py
src/routes/mail_routes.py
src/routes/mobile_routes.py
src/routes/recibos_routes.py
src/utils/__init__.py