Metadata-Version: 2.1
Name: project-americana-api-rest
Version: 1.0.0
Summary: API REST para Project Americana
Home-page: https://github.com/TU_USUARIO/project-americana-api-rest
Author: Tu Nombre
Author-email: tu_correo@ejemplo.com
